django_zencache.py
django_zencache-0.1.0.dist-info/METADATA
django_zencache-0.1.0.dist-info/WHEEL
django_zencache-0.1.0.dist-info/top_level.txt
django_zencache-0.1.0.dist-info/RECORD
